{
  "updated": "2026-06-11 20:40 svensk tid",
  "stocks": {
    "INVE-B.ST": {
      "price": 375.85,
      "change": -0.31,
      "rsi": 43.1,
      "ma50": 371.45,
      "ma200": 333.67,
      "macd": 2.337,
      "bollinger": 0.42,
      "w52": 0.91,
      "trend": 0.55,
      "signal": "HALL",
      "styrka": 6,
      "ok": true,
      "ath": null,
      "momentum": null,
      "earnings_date": null,
      "news_sentiment": "neutral",
      "news_summary": "Generic sector commentary with no INVE-B.ST specific catalysts identified",
      "news_score": 0
    },
    "ATCO-B.ST": {
      "price": 161.25,
      "change": 1.13,
      "rsi": 57.1,
      "ma50": 156.8,
      "ma200": 149.36,
      "macd": 1.127,
      "bollinger": 0.77,
      "w52": 0.86,
      "trend": 0.6,
      "signal": "HALL",
      "styrka": 6,
      "ok": true,
      "ath": null,
      "momentum": null,
      "earnings_date": null,
      "news_sentiment": null,
      "news_summary": null,
      "news_score": 0
    },
    "SWED-A.ST": {
      "price": 338.8,
      "change": 0.41,
      "rsi": 43.3,
      "ma50": 329.89,
      "ma200": 293.73,
      "macd": 2.443,
      "bollinger": 0.58,
      "w52": 0.93,
      "trend": 0.6,
      "signal": "HALL",
      "styrka": 6,
      "ok": true,
      "ath": null,
      "momentum": null,
      "earnings_date": null,
      "news_sentiment": "neutral",
      "news_summary": "Retrospective commentary and earnings discussion without specific surprises",
      "news_score": 0
    },
    "SAAB-B.ST": {
      "price": 536.0,
      "change": 2.17,
      "rsi": 52.1,
      "ma50": 562.86,
      "ma200": 571.65,
      "macd": -8.193,
      "bollinger": 0.59,
      "w52": 0.32,
      "trend": 0.65,
      "signal": "HALL",
      "styrka": 5,
      "ok": true,
      "ath": null,
      "momentum": null,
      "earnings_date": null,
      "news_sentiment": "positive",
      "news_summary": "Airbus consideration plus defense wins support upside",
      "news_score": 1
    },
    "ERIC-B.ST": {
      "price": 112.7,
      "change": 1.17,
      "rsi": 30.9,
      "ma50": 113.69,
      "ma200": 95.32,
      "macd": 0.433,
      "bollinger": 0.07,
      "w52": 0.75,
      "trend": 0.55,
      "signal": "KOP",
      "styrka": 10,
      "ok": true,
      "ath": null,
      "momentum": null,
      "earnings_date": null,
      "news_sentiment": "neutral",
      "news_summary": "Generic valuation question; no material catalysts or news",
      "news_score": 0
    },
    "VOLV-B.ST": {
      "price": 310.1,
      "change": 1.34,
      "rsi": 46.7,
      "ma50": 317.55,
      "ma200": 292.29,
      "macd": -0.637,
      "bollinger": 0.16,
      "w52": 0.71,
      "trend": 0.5,
      "signal": "HALL",
      "styrka": 6,
      "ok": true,
      "ath": null,
      "momentum": null,
      "earnings_date": null,
      "news_sentiment": "negative",
      "news_summary": "Automotive sector weakness drags VOLV-B; sector-wide headwind.",
      "news_score": -1
    },
    "KINV-B.ST": {
      "price": 57.16,
      "change": 0.32,
      "rsi": 50.9,
      "ma50": 54.12,
      "ma200": 71.27,
      "macd": 1.108,
      "bollinger": 0.55,
      "w52": 0.21,
      "trend": 0.6,
      "signal": "SALJ",
      "styrka": 3,
      "ok": true,
      "ath": null,
      "momentum": null,
      "earnings_date": null,
      "news_sentiment": "neutral",
      "news_summary": "Earnings calls lack specific financial metrics or guidance changes",
      "news_score": 0
    },
    "HM-B.ST": {
      "price": 167.2,
      "change": 1.18,
      "rsi": 57.5,
      "ma50": 166.51,
      "ma200": 168.12,
      "macd": 0.07,
      "bollinger": 0.94,
      "w52": 0.67,
      "trend": 0.6,
      "signal": "SALJ",
      "styrka": 4,
      "ok": true,
      "ath": null,
      "momentum": null,
      "earnings_date": null,
      "news_sentiment": "neutral",
      "news_summary": "Mixed valuation commentary and generic tariff sector risks",
      "news_score": 0
    },
    "SEB-A.ST": {
      "price": 183.15,
      "change": -0.19,
      "rsi": 42.1,
      "ma50": 181.53,
      "ma200": 176.88,
      "macd": 0.499,
      "bollinger": 0.45,
      "w52": 0.79,
      "trend": 0.65,
      "signal": "HALL",
      "styrka": 6,
      "ok": true,
      "ath": null,
      "momentum": null,
      "earnings_date": null,
      "news_sentiment": "neutral",
      "news_summary": "Generic portfolio commentary and valuation discussion, no catalysts",
      "news_score": 0
    },
    "TEL2-B.ST": {
      "price": 183.25,
      "change": 1.55,
      "rsi": 51.3,
      "ma50": 182.06,
      "ma200": 164.39,
      "macd": -0.848,
      "bollinger": 0.77,
      "w52": 0.86,
      "trend": 0.6,
      "signal": "HALL",
      "styrka": 6,
      "ok": true,
      "ath": null,
      "momentum": null,
      "earnings_date": null,
      "news_sentiment": "positive",
      "news_summary": "Analyst rating upgrade to Strong Buy supports near-term bullish momentum",
      "news_score": 1
    },
    "BEAMMW-B.ST": {
      "price": 16.58,
      "change": 9.8,
      "rsi": 62.7,
      "ma50": 12.55,
      "ma200": 9.0,
      "macd": 0.864,
      "bollinger": 0.76,
      "w52": 0.84,
      "trend": 0.6,
      "signal": "HALL",
      "styrka": 5,
      "ok": true,
      "ath": null,
      "momentum": null,
      "earnings_date": null,
      "news_sentiment": null,
      "news_summary": null,
      "news_score": 0
    },
    "NANEXA.ST": {
      "price": 4.46,
      "change": 0.22,
      "rsi": 78.1,
      "ma50": 3.85,
      "ma200": 3.08,
      "macd": 0.203,
      "bollinger": 0.78,
      "w52": 0.86,
      "trend": 0.7,
      "signal": "HALL",
      "styrka": 6,
      "ok": true,
      "ath": null,
      "momentum": null,
      "earnings_date": null,
      "news_sentiment": "positive",
      "news_summary": "Moderna partnership worth $503M represents major contract win",
      "news_score": 2
    },
    "INDU-C.ST": {
      "price": 494.8,
      "change": 0.0,
      "rsi": 47.2,
      "ma50": 486.51,
      "ma200": 429.58,
      "macd": 3.784,
      "bollinger": 0.48,
      "w52": 0.94,
      "trend": 0.5,
      "signal": "HALL",
      "styrka": 6,
      "ok": true,
      "ath": null,
      "momentum": null,
      "earnings_date": null,
      "news_sentiment": "neutral",
      "news_summary": "Net margin stability supports value case; earnings decline noted.",
      "news_score": 0
    },
    "ASML": {
      "price": 1857.9,
      "change": 7.13,
      "rsi": 70.3,
      "ma50": 1525.12,
      "ma200": 1236.14,
      "macd": 77.058,
      "bollinger": 1,
      "w52": 1.0,
      "trend": 0.65,
      "signal": "HALL",
      "styrka": 6,
      "ok": true,
      "ath": null,
      "momentum": "MOMENTUM_UP",
      "earnings_date": null,
      "news_sentiment": "positive",
      "news_summary": "Oracle earnings beat drives semiconductor demand signals; Musk engagement adds optionality",
      "news_score": 1
    },
    "SAP": {
      "price": 163.75,
      "change": -3.85,
      "rsi": 41.0,
      "ma50": 172.62,
      "ma200": 217.85,
      "macd": 0.598,
      "bollinger": 0.05,
      "w52": 0.02,
      "trend": 0.45,
      "signal": "HALL",
      "styrka": 6,
      "ok": true,
      "ath": null,
      "momentum": null,
      "earnings_date": null,
      "news_sentiment": "negative",
      "news_summary": "Sector headwind from Oracle's capex plans creating sympathy selloff",
      "news_score": -1
    },
    "NVO": {
      "price": 43.83,
      "change": 2.39,
      "rsi": 48.0,
      "ma50": 42.26,
      "ma200": 47.14,
      "macd": -0.089,
      "bollinger": 0.48,
      "w52": 0.21,
      "trend": 0.45,
      "signal": "SALJ",
      "styrka": 2,
      "ok": true,
      "ath": null,
      "momentum": null,
      "earnings_date": null,
      "news_sentiment": "neutral",
      "news_summary": "Wegovy UK approval offset by cybersecurity breach concerns",
      "news_score": 0
    },
    "LVMUY": {
      "price": 115.47,
      "change": 2.87,
      "rsi": 57.3,
      "ma50": 109.51,
      "ma200": 124.85,
      "macd": 1.106,
      "bollinger": 1,
      "w52": 0.3,
      "trend": 0.6,
      "signal": "SALJ",
      "styrka": 3,
      "ok": true,
      "ath": null,
      "momentum": null,
      "earnings_date": null,
      "news_sentiment": "neutral",
      "news_summary": "LVMH investment in AI robotics startup is minor strategic play",
      "news_score": 0
    },
    "SHEL": {
      "price": 86.54,
      "change": 0.58,
      "rsi": 51.9,
      "ma50": 87.38,
      "ma200": 77.98,
      "macd": -0.133,
      "bollinger": 0.67,
      "w52": 0.74,
      "trend": 0.5,
      "signal": "HALL",
      "styrka": 6,
      "ok": true,
      "ath": null,
      "momentum": null,
      "earnings_date": null,
      "news_sentiment": "positive",
      "news_summary": "Strong Q1 earnings, CEO bullish on oil prices, solid valuation",
      "news_score": 1
    },
    "SIEGY": {
      "price": 152.36,
      "change": 2.52,
      "rsi": 45.4,
      "ma50": 147.83,
      "ma200": 140.83,
      "macd": 1.101,
      "bollinger": 0.3,
      "w52": 0.79,
      "trend": 0.55,
      "signal": "HALL",
      "styrka": 6,
      "ok": true,
      "ath": null,
      "momentum": null,
      "earnings_date": null,
      "news_sentiment": "neutral",
      "news_summary": "No SIEGY-specific news found; generic sector coverage only.",
      "news_score": 0
    },
    "NSRGY": {
      "price": 100.13,
      "change": 0.84,
      "rsi": 47.9,
      "ma50": 98.58,
      "ma200": 94.94,
      "macd": -0.236,
      "bollinger": 0.61,
      "w52": 0.78,
      "trend": 0.5,
      "signal": "SALJ",
      "styrka": 4,
      "ok": true,
      "ath": null,
      "momentum": null,
      "earnings_date": null,
      "news_sentiment": "neutral",
      "news_summary": "Generic consumer sector news unrelated to NSRGY operations",
      "news_score": 0
    },
    "EADSY": {
      "price": 51.34,
      "change": 2.15,
      "rsi": 62.2,
      "ma50": 50.14,
      "ma200": 54.32,
      "macd": 0.176,
      "bollinger": 0.76,
      "w52": 0.38,
      "trend": 0.5,
      "signal": "SALJ",
      "styrka": 3,
      "ok": true,
      "ath": null,
      "momentum": null,
      "earnings_date": null,
      "news_sentiment": "negative",
      "news_summary": "FCAS fighter jet program collapse; fuel crisis threatens airline customers",
      "news_score": -1
    },
    "AZN": {
      "price": 182.38,
      "change": 1.91,
      "rsi": 40.4,
      "ma50": 189.58,
      "ma200": 180.87,
      "macd": -1.854,
      "bollinger": 0.42,
      "w52": 0.64,
      "trend": 0.5,
      "signal": "KOP",
      "styrka": 8,
      "ok": true,
      "ath": null,
      "momentum": null,
      "earnings_date": null,
      "news_sentiment": "positive",
      "news_summary": "AZN GLP-1 oral candidate advancing to late-stage trials",
      "news_score": 1
    },
    "RELX": {
      "price": 33.29,
      "change": -2.02,
      "rsi": 49.8,
      "ma50": 34.04,
      "ma200": 38.16,
      "macd": 0.079,
      "bollinger": 0.44,
      "w52": 0.24,
      "trend": 0.4,
      "signal": "HALL",
      "styrka": 5,
      "ok": true,
      "ath": null,
      "momentum": null,
      "earnings_date": null,
      "news_sentiment": "neutral",
      "news_summary": "No material RELX-specific catalysts identified in headlines",
      "news_score": 0
    },
    "BAESY": {
      "price": 105.1,
      "change": 1.2,
      "rsi": 49.7,
      "ma50": 110.32,
      "ma200": 104.64,
      "macd": -1.398,
      "bollinger": 0.59,
      "w52": 0.54,
      "trend": 0.55,
      "signal": "KOP",
      "styrka": 8,
      "ok": true,
      "ath": null,
      "momentum": null,
      "earnings_date": null,
      "news_sentiment": "neutral",
      "news_summary": "Mixed signals: strong orders offset by valuation concerns and slowing growth",
      "news_score": 0
    },
    "NVDA": {
      "price": 202.27,
      "change": 0.92,
      "rsi": 37.1,
      "ma50": 206.06,
      "ma200": 188.91,
      "macd": -0.867,
      "bollinger": 0.1,
      "w52": 0.65,
      "trend": 0.35,
      "signal": "KOP",
      "styrka": 8,
      "ok": true,
      "ath": null,
      "momentum": null,
      "earnings_date": null,
      "news_sentiment": "neutral",
      "news_summary": "Generic market commentary, no company-specific catalysts identified.",
      "news_score": 0
    },
    "AAPL": {
      "price": 295.48,
      "change": 1.34,
      "rsi": 41.4,
      "ma50": 284.64,
      "ma200": 266.14,
      "macd": 3.332,
      "bollinger": 0.19,
      "w52": 0.84,
      "trend": 0.55,
      "signal": "KOP",
      "styrka": 8,
      "ok": true,
      "ath": null,
      "momentum": null,
      "earnings_date": null,
      "news_sentiment": "negative",
      "news_summary": "Mag 7 selloff pressures AAPL; sector headwind outweighs portfolio inclusion",
      "news_score": -1
    },
    "MSFT": {
      "price": 387.86,
      "change": -2.39,
      "rsi": 37.8,
      "ma50": 410.7,
      "ma200": 452.4,
      "macd": -2.461,
      "bollinger": 0.0,
      "w52": 0.17,
      "trend": 0.4,
      "signal": "SALJ",
      "styrka": 4,
      "ok": true,
      "ath": null,
      "momentum": null,
      "earnings_date": null,
      "news_sentiment": "negative",
      "news_summary": "Magnificent Seven sector weakness; MSFT caught in broader selloff.",
      "news_score": -1
    },
    "AMZN": {
      "price": 239.1,
      "change": 0.46,
      "rsi": 24.0,
      "ma50": 254.17,
      "ma200": 232.45,
      "macd": -4.416,
      "bollinger": 0.06,
      "w52": 0.53,
      "trend": 0.35,
      "signal": "KOP",
      "styrka": 10,
      "ok": true,
      "ath": null,
      "momentum": null,
      "earnings_date": null,
      "news_sentiment": "neutral",
      "news_summary": "Generic market commentary with no AMZN-specific catalysts identified.",
      "news_score": 0
    },
    "GOOGL": {
      "price": 353.37,
      "change": -0.84,
      "rsi": 27.8,
      "ma50": 360.72,
      "ma200": 306.78,
      "macd": -2.704,
      "bollinger": 0.07,
      "w52": 0.79,
      "trend": 0.3,
      "signal": "KOP",
      "styrka": 8,
      "ok": true,
      "ath": null,
      "momentum": null,
      "earnings_date": null,
      "news_sentiment": "neutral",
      "news_summary": "Mixed signals: positive portfolio inclusion offset by sector selloff",
      "news_score": 0
    },
    "META": {
      "price": 566.62,
      "change": -0.76,
      "rsi": 37.0,
      "ma50": 622.04,
      "ma200": 658.35,
      "macd": -11.521,
      "bollinger": 0,
      "w52": 0.16,
      "trend": 0.45,
      "signal": "SALJ",
      "styrka": 4,
      "ok": true,
      "ath": null,
      "momentum": null,
      "earnings_date": null,
      "news_sentiment": "negative",
      "news_summary": "Canada youth ban threatens 3% revenue; sector weakness offsets AI credibility",
      "news_score": -1
    },
    "TSLA": {
      "price": 392.57,
      "change": 2.88,
      "rsi": 41.4,
      "ma50": 397.67,
      "ma200": 415.39,
      "macd": -2.763,
      "bollinger": 0.14,
      "w52": 0.5,
      "trend": 0.45,
      "signal": "HALL",
      "styrka": 5,
      "ok": true,
      "ath": null,
      "momentum": null,
      "earnings_date": null,
      "news_sentiment": "neutral",
      "news_summary": "Generic commentary and SpaceX news; no TSLA-specific catalysts",
      "news_score": 0
    },
    "JPM": {
      "price": 313.46,
      "change": 1.4,
      "rsi": 61.4,
      "ma50": 306.02,
      "ma200": 304.43,
      "macd": 1.97,
      "bollinger": 0.91,
      "w52": 0.73,
      "trend": 0.55,
      "signal": "SALJ",
      "styrka": 4,
      "ok": true,
      "ath": null,
      "momentum": null,
      "earnings_date": null,
      "news_sentiment": "neutral",
      "news_summary": "No JPM-specific catalysts; unrelated sector news only",
      "news_score": 0
    },
    "BRK-B": {
      "price": 484.87,
      "change": 0.25,
      "rsi": 55.1,
      "ma50": 477.72,
      "ma200": 490.4,
      "macd": 1.715,
      "bollinger": 0.67,
      "w52": 0.47,
      "trend": 0.45,
      "signal": "HALL",
      "styrka": 5,
      "ok": true,
      "ath": null,
      "momentum": null,
      "earnings_date": null,
      "news_sentiment": "neutral",
      "news_summary": "Generic commentary and opinion pieces; no company-specific catalysts",
      "news_score": 0
    },
    "LLY": {
      "price": 1163.93,
      "change": 2.43,
      "rsi": 72.3,
      "ma50": 992.27,
      "ma200": 953.75,
      "macd": 46.192,
      "bollinger": 0.9,
      "w52": 1.0,
      "trend": 0.5,
      "signal": "SALJ",
      "styrka": 3,
      "ok": true,
      "ath": null,
      "momentum": null,
      "earnings_date": null,
      "news_sentiment": "negative",
      "news_summary": "Employers reconsidering GLP-1 coverage threatens LLY's key revenue driver",
      "news_score": -1
    },
    "BYDDF": {
      "price": 10.99,
      "change": -0.54,
      "rsi": 38.3,
      "ma50": 12.73,
      "ma200": 12.88,
      "macd": -0.438,
      "bollinger": 0.07,
      "w52": 0.0,
      "trend": 0.3,
      "signal": "HALL",
      "styrka": 6,
      "ok": true,
      "ath": null,
      "momentum": null,
      "earnings_date": null,
      "news_sentiment": "positive",
      "news_summary": "BYD attracts government EV investment; expansion beyond China story",
      "news_score": 1
    },
    "TSM": {
      "price": 415.99,
      "change": 1.77,
      "rsi": 53.1,
      "ma50": 396.47,
      "ma200": 329.14,
      "macd": 7.508,
      "bollinger": 0.47,
      "w52": 0.87,
      "trend": 0.6,
      "signal": "HALL",
      "styrka": 6,
      "ok": true,
      "ath": null,
      "momentum": null,
      "earnings_date": null,
      "news_sentiment": "neutral",
      "news_summary": "No TSM-specific catalysts; unrelated competitor and supplier news",
      "news_score": 0
    },
    "CL=F": {
      "price": 87.69,
      "change": -2.6,
      "rsi": 36.5,
      "ma50": 97.05,
      "ma200": 73.3,
      "macd": -2.321,
      "bollinger": 0.22,
      "w52": 0.56,
      "trend": 0.5,
      "signal": "KOP",
      "styrka": 7,
      "ok": true,
      "ath": 147.27,
      "momentum": null,
      "earnings_date": null,
      "news_sentiment": "positive",
      "news_summary": "Iran escalation fears easing; oil prices supported by demand relief",
      "news_score": 1
    },
    "GC=F": {
      "price": 4173.0,
      "change": 1.58,
      "rsi": 27.9,
      "ma50": 4600.78,
      "ma200": 4415.79,
      "macd": -110.865,
      "bollinger": 0,
      "w52": 0.44,
      "trend": 0.35,
      "signal": "KOP",
      "styrka": 8,
      "ok": true,
      "ath": 5586.2,
      "momentum": null,
      "earnings_date": null,
      "news_sentiment": "negative",
      "news_summary": "Gold and silver hit 6-month lows amid geopolitical de-escalation",
      "news_score": -1
    },
    "SI=F": {
      "price": 66.04,
      "change": 2.23,
      "rsi": 20.2,
      "ma50": 75.77,
      "ma200": 67.05,
      "macd": -2.961,
      "bollinger": 0.09,
      "w52": 0.38,
      "trend": 0.35,
      "signal": "KOP",
      "styrka": 10,
      "ok": true,
      "ath": 121.3,
      "momentum": null,
      "earnings_date": null,
      "news_sentiment": "positive",
      "news_summary": "Analyst upside target of 51.79% supports bullish case",
      "news_score": 1
    },
    "BTC-USD": {
      "price": 63437.04,
      "change": 3.23,
      "rsi": 24.2,
      "ma50": 74710.75,
      "ma200": 78007.51,
      "macd": -3998.649,
      "bollinger": 0.28,
      "w52": 0.04,
      "trend": 0.3,
      "signal": "KOP",
      "styrka": 9,
      "ok": true,
      "ath": 126198.07,
      "momentum": null,
      "earnings_date": null,
      "news_sentiment": "negative",
      "news_summary": "Geopolitical tension and analyst skepticism weigh on BTC",
      "news_score": -1
    },
    "ETH-USD": {
      "price": 1682.65,
      "change": 3.86,
      "rsi": 27.3,
      "ma50": 2106.77,
      "ma200": 2427.29,
      "macd": -142.18,
      "bollinger": 0.26,
      "w52": 0.04,
      "trend": 0.35,
      "signal": "KOP",
      "styrka": 7,
      "ok": true,
      "ath": 4953.73,
      "momentum": null,
      "earnings_date": null,
      "news_sentiment": "neutral",
      "news_summary": "Mixed signals: stablecoin adoption positive, ETF outflows negative, price recovery neutral",
      "news_score": 0
    },
    "CSPX.L": {
      "price": 784.72,
      "change": -0.41,
      "rsi": 40.7,
      "ma50": 774.55,
      "ma200": 736.62,
      "macd": 4.401,
      "bollinger": 0.06,
      "w52": 0.82,
      "trend": 0.45,
      "signal": "KOP",
      "styrka": 8,
      "ok": true,
      "ath": null,
      "momentum": null,
      "earnings_date": null,
      "news_sentiment": "neutral",
      "news_summary": "Generic market commentary unrelated to CSPX fundamentals.",
      "news_score": 0
    },
    "EQQQ.DE": {
      "price": 610.8,
      "change": 0.44,
      "rsi": 39.5,
      "ma50": 584.35,
      "ma200": 536.56,
      "macd": 8.603,
      "bollinger": 0.23,
      "w52": 0.82,
      "trend": 0.55,
      "signal": "KOP",
      "styrka": 8,
      "ok": true,
      "ath": null,
      "momentum": null,
      "earnings_date": null,
      "news_sentiment": "neutral",
      "news_summary": "Generic market commentary without EQQQ.DE-specific catalysts",
      "news_score": 0
    },
    "JEDI.DE": {
      "price": 93.6,
      "change": 6.03,
      "rsi": 37.3,
      "ma50": 91.68,
      "ma200": 66.9,
      "macd": 0.152,
      "bollinger": 0.25,
      "w52": 0.7,
      "trend": 0.5,
      "signal": "KOP",
      "styrka": 8,
      "ok": true,
      "ath": null,
      "momentum": null,
      "earnings_date": null,
      "news_sentiment": "neutral",
      "news_summary": "No JEDI.DE-specific news; unrelated sector commentary only",
      "news_score": 0
    },
    "XACT-OMXS30.ST": {
      "price": 458.55,
      "change": 0.52,
      "rsi": 38.7,
      "ma50": 460.04,
      "ma200": 426.45,
      "macd": 0.327,
      "bollinger": 0.23,
      "w52": 0.84,
      "trend": 0.45,
      "signal": "KOP",
      "styrka": 8,
      "ok": true,
      "ath": null,
      "momentum": null,
      "earnings_date": null,
      "news_sentiment": null,
      "news_summary": null,
      "news_score": 0
    },
    "XACTHDIV.ST": {
      "price": 163.76,
      "change": 0.16,
      "rsi": 33.9,
      "ma50": 165.12,
      "ma200": 156.7,
      "macd": -0.323,
      "bollinger": 0.27,
      "w52": 0.81,
      "trend": 0.55,
      "signal": "KOP",
      "styrka": 8,
      "ok": true,
      "ath": null,
      "momentum": null,
      "earnings_date": null,
      "news_sentiment": null,
      "news_summary": null,
      "news_score": 0
    },
    "SMH.DE": {
      "price": 92.18,
      "change": -0.66,
      "rsi": 57.5,
      "ma50": 80.06,
      "ma200": 59.93,
      "macd": 4.296,
      "bollinger": 0.48,
      "w52": 0.85,
      "trend": 0.55,
      "signal": "HALL",
      "styrka": 6,
      "ok": true,
      "ath": null,
      "momentum": null,
      "earnings_date": null,
      "news_sentiment": "neutral",
      "news_summary": "Generic sector commentary; no SMH.DE-specific catalysts identified.",
      "news_score": 0
    },
    "DFNS.L": {
      "price": 61.67,
      "change": 1.58,
      "rsi": 48.7,
      "ma50": 65.38,
      "ma200": 65.03,
      "macd": -1.05,
      "bollinger": 0.35,
      "w52": 0.37,
      "trend": 0.5,
      "signal": "SALJ",
      "styrka": 4,
      "ok": true,
      "ath": null,
      "momentum": null,
      "earnings_date": null,
      "news_sentiment": "positive",
      "news_summary": "Defense sector tailwinds from geopolitical tension and autonomous weapons investment",
      "news_score": 1
    },
    "VWRL.L": {
      "price": 134.13,
      "change": 0.31,
      "rsi": 47.8,
      "ma50": 131.38,
      "ma200": 124.46,
      "macd": 0.962,
      "bollinger": 0.22,
      "w52": 0.86,
      "trend": 0.55,
      "signal": "HALL",
      "styrka": 6,
      "ok": true,
      "ath": null,
      "momentum": null,
      "earnings_date": null,
      "news_sentiment": "neutral",
      "news_summary": "Sector headwinds noted; no company-specific catalysts identified",
      "news_score": 0
    },
    "IS3N.DE": {
      "price": 46.44,
      "change": 1.11,
      "rsi": 49.0,
      "ma50": 45.17,
      "ma200": 40.48,
      "macd": 0.379,
      "bollinger": 0.38,
      "w52": 0.82,
      "trend": 0.5,
      "signal": "HALL",
      "styrka": 6,
      "ok": true,
      "ath": null,
      "momentum": null,
      "earnings_date": null,
      "news_sentiment": "neutral",
      "news_summary": "Macroeconomic headwinds offset by emerging market tailwinds",
      "news_score": 0
    },
    "IQQH.DE": {
      "price": 10.08,
      "change": 1.57,
      "rsi": 31.5,
      "ma50": 10.22,
      "ma200": 8.79,
      "macd": 0.02,
      "bollinger": 0.1,
      "w52": 0.71,
      "trend": 0.5,
      "signal": "KOP",
      "styrka": 10,
      "ok": true,
      "ath": null,
      "momentum": null,
      "earnings_date": null,
      "news_sentiment": "neutral",
      "news_summary": "Generic sector trends; no IQQH.DE-specific catalysts identified",
      "news_score": 0
    },
    "IGLN.L": {
      "price": 79.17,
      "change": -1.15,
      "rsi": 24.9,
      "ma50": 89.28,
      "ma200": 85.79,
      "macd": -2.301,
      "bollinger": 0,
      "w52": 0.4,
      "trend": 0.3,
      "signal": "KOP",
      "styrka": 8,
      "ok": true,
      "ath": null,
      "momentum": null,
      "earnings_date": null,
      "news_sentiment": "neutral",
      "news_summary": "No company-specific news for IGLN.L; generic commodity commentary only",
      "news_score": 0
    }
  },
  "fear_greed": {
    "value": 12,
    "classification": "Extreme Fear"
  },
  "trump_mentions": []
}